pydevmate/__init__.py
pydevmate/cacheit.py
pydevmate/colors.py
pydevmate/convertIt.py
pydevmate/debugit.py
pydevmate/infos.py
pydevmate/lazyit.py
pydevmate/logit.py
pydevmate/memit.py
pydevmate/saveit.py
pydevmate/timeit.py
pydevmate-0.0.3.dist-info/licenses/LICENSE
pydevmate-0.0.3.dist-info/METADATA
pydevmate-0.0.3.dist-info/WHEEL
pydevmate-0.0.3.dist-info/top_level.txt
pydevmate-0.0.3.dist-info/RECORD
