Metadata-Version: 2.4
Name: PyDevMate
Version: 0.0.3
Summary: A library of utilities for python.
Home-page: https://github.com/lounisbou/PyDevMate
Author: LounisBou
Author-email: LounisBou <lounis.bou@gmail.com>
License-Expression: MIT
Project-URL: Homepage, https://github.com/lounisbou/PyDevMate
Project-URL: Repository, https://github.com/lounisbou/PyDevMate
Project-URL: Issues, https://github.com/lounisbou/PyDevMate/issues
Keywords: utilities,decorators,caching,logging,monitoring,debugging
Classifier: Programming Language :: Python :: 3
Classifier: Programming Language :: Python :: 3.6
Classifier: Programming Language :: Python :: 3.7
Classifier: Programming Language :: Python :: 3.8
Classifier: Programming Language :: Python :: 3.9
Classifier: Programming Language :: Python :: 3.10
Classifier: Programming Language :: Python :: 3.11
Classifier: Programming Language :: Python :: 3.12
Classifier: Operating System :: OS Independent
Classifier: Intended Audience :: Developers
Classifier: Topic :: Software Development :: Libraries :: Python Modules
Classifier: Topic :: Utilities
Requires-Python: >=3.6
License-File: LICENSE
Requires-Dist: diskcache>=5.6.3
Requires-Dist: psutil>=6.1.0
Requires-Dist: redis>=5.2.0
Requires-Dist: termcolor>=2.5.0
Dynamic: author
Dynamic: home-page
Dynamic: license-file
Dynamic: requires-python
